{"slug":"n-kedah-anak-bukit","seat_type":"state","state":"Kedah","current_name":"Anak Bukit","current_seat":"N.15 Anak Bukit","all_names":["Anak Bukit"],"n_names":1,"first_year":1974,"last_year":2023,"n_contests":11,"founding":{"year":1974,"party":"PAS","party_uid":"004-PAS","coalition":"BN","coalition_uid":"001-BN","name":"Abdul Wahab bin Sulaiman","candidate_uid":"MX96D","seat_name":"Anak Bukit"},"current_holder":{"party":"PAS","party_uid":"004-PAS","coalition":"PN","coalition_uid":"011-PN","name":"Rashidi bin Razak","candidate_uid":"7XY7S","year":2023,"margin_perc":57.27,"win_perc":78.6,"run_party":"UMNO","run_party_uid":"001-UMNO","run_perc":21.4,"turnout":76.2,"uncontested":false},"parties_won":[{"party":"PAS","party_uid":"004-PAS","coalition":"BN","coalition_uid":"001-BN","wins":8},{"party":"UMNO","party_uid":"001-UMNO","coalition":"BN","coalition_uid":"001-BN","wins":2},{"party":"BERSATU","party_uid":"107-BERSATU","coalition":"PH","coalition_uid":"007-PH","wins":1}],"n_distinct_winning_parties":3,"dominant_party":{"party":"PAS","party_uid":"004-PAS","coalition":"BN","coalition_uid":"001-BN","wins":8},"closest":{"year":2004,"election":"SE-11","win_party":"PAS","win_party_uid":"004-PAS","win_coalition":"BA","run_party":"UMNO","run_party_uid":"001-UMNO","run_coalition":"BN","win_perc":50.2,"run_perc":49.8,"margin_perc":0.47},"biggest_swing":{"year":2023,"election":"SE-15","swing_pp":36.4,"from_coalition":"PH","to_coalition":"PN","flipped":true,"win_party":"PAS","win_party_uid":"004-PAS","win_coalition":"PN","win_perc":78.6,"run_party":"UMNO","run_party_uid":"001-UMNO","run_coalition":"BN","run_perc":21.4,"prev_win_perc":42.2},"marginality_rank":{"rank":453,"total":518,"scope":"state seats, SE-15"},"turnout_ref":{"national_avg":69.1,"latest_year":2023},"timeline":[{"year":1974,"election":"SE-04","date":"1974-08-24","seat_name":"Anak Bukit","win_party":"PAS","win_party_uid":"004-PAS","win_coalition":"BN","win_coalition_uid":"001-BN","win_name":"Abdul Wahab bin Sulaiman","win_perc":73.8,"run_party":"PSRM","run_party_uid":"009-PSRM","run_coalition":"ALONE","run_perc":16.6,"margin_perc":57.25,"turnout":68.4,"n_candidates":3,"uncontested":false,"electorate":16924},{"year":1978,"election":"SE-05","date":"1978-07-08","seat_name":"Anak Bukit","win_party":"PAS","win_party_uid":"004-PAS","win_coalition":"ALONE","win_coalition_uid":"000-ALONE","win_name":"Abdul Wahab bin Sulaiman","win_perc":54.3,"run_party":"UMNO","run_party_uid":"001-UMNO","run_coalition":"BN","run_perc":45.7,"margin_perc":8.52,"turnout":76.6,"n_candidates":2,"uncontested":false,"electorate":18841},{"year":1982,"election":"SE-06","date":"1982-04-22","seat_name":"Anak Bukit","win_party":"UMNO","win_party_uid":"001-UMNO","win_coalition":"BN","win_coalition_uid":"001-BN","win_name":"Karia @ Zakaria bin Said @ Mohd Said","win_perc":55.7,"run_party":"PAS","run_party_uid":"004-PAS","run_coalition":"ALONE","run_perc":44.3,"margin_perc":11.49,"turnout":77.5,"n_candidates":2,"uncontested":false,"electorate":21496},{"year":1995,"election":"SE-09","date":"1995-04-24","seat_name":"Anak Bukit","win_party":"UMNO","win_party_uid":"001-UMNO","win_coalition":"BN","win_coalition_uid":"001-BN","win_name":"Abdullah Hasnan bin Kamaruddin","win_perc":52.1,"run_party":"PAS","run_party_uid":"004-PAS","run_coalition":"APU","run_perc":47.9,"margin_perc":4.2,"turnout":75.3,"n_candidates":2,"uncontested":false,"electorate":18297},{"year":1999,"election":"SE-10","date":"1999-11-29","seat_name":"Anak Bukit","win_party":"PAS","win_party_uid":"004-PAS","win_coalition":"BA","win_coalition_uid":"007-BA","win_name":"Fadzil bin Md. Noor","win_perc":56.1,"run_party":"UMNO","run_party_uid":"001-UMNO","run_coalition":"BN","run_perc":43.9,"margin_perc":12.17,"turnout":77.9,"n_candidates":2,"uncontested":false,"electorate":19723},{"year":2002,"election":"BY-ELECTION","date":"2002-07-18","seat_name":"Anak Bukit","win_party":"PAS","win_party_uid":"004-PAS","win_coalition":"BA","win_coalition_uid":"007-BA","win_name":"Amiruddin bin Hamzah","win_perc":51.6,"run_party":"UMNO","run_party_uid":"001-UMNO","run_coalition":"BN","run_perc":48.4,"margin_perc":3.16,"turnout":83.6,"n_candidates":2,"uncontested":false,"electorate":19399},{"year":2004,"election":"SE-11","date":"2004-03-21","seat_name":"Anak Bukit","win_party":"PAS","win_party_uid":"004-PAS","win_coalition":"BA","win_coalition_uid":"007-BA","win_name":"Amiruddin bin Hamzah","win_perc":50.2,"run_party":"UMNO","run_party_uid":"001-UMNO","run_coalition":"BN","run_perc":49.8,"margin_perc":0.47,"turnout":84.2,"n_candidates":2,"uncontested":false,"electorate":24523},{"year":2008,"election":"SE-12","date":"2008-03-08","seat_name":"Anak Bukit","win_party":"PAS","win_party_uid":"004-PAS","win_coalition":"PR","win_coalition_uid":"007-PR","win_name":"Amiruddin bin Hamzah","win_perc":59.0,"run_party":"UMNO","run_party_uid":"001-UMNO","run_coalition":"BN","run_perc":41.0,"margin_perc":17.97,"turnout":83.5,"n_candidates":2,"uncontested":false,"electorate":26213},{"year":2013,"election":"SE-13","date":"2013-05-05","seat_name":"Anak Bukit","win_party":"PAS","win_party_uid":"004-PAS","win_coalition":"PR","win_coalition_uid":"007-PR","win_name":"Amiruddin bin Hamzah","win_perc":55.5,"run_party":"UMNO","run_party_uid":"001-UMNO","run_coalition":"BN","run_perc":44.2,"margin_perc":11.26,"turnout":87.3,"n_candidates":3,"uncontested":false,"electorate":28981},{"year":2018,"election":"SE-14","date":"2018-05-09","seat_name":"Anak Bukit","win_party":"BERSATU","win_party_uid":"107-BERSATU","win_coalition":"PH","win_coalition_uid":"007-PH","win_name":"Amiruddin bin Hamzah","win_perc":42.2,"run_party":"PAS","run_party_uid":"004-PAS","run_coalition":"GS","run_perc":35.4,"margin_perc":6.79,"turnout":83.7,"n_candidates":3,"uncontested":false,"electorate":28223},{"year":2023,"election":"SE-15","date":"2023-08-12","seat_name":"Anak Bukit","win_party":"PAS","win_party_uid":"004-PAS","win_coalition":"PN","win_coalition_uid":"011-PN","win_name":"Rashidi bin Razak","win_perc":78.6,"run_party":"UMNO","run_party_uid":"001-UMNO","run_coalition":"BN","run_perc":21.4,"margin_perc":57.27,"turnout":76.2,"n_candidates":2,"uncontested":false,"electorate":36491}]}