{"slug":"n-negeri-sembilan-klawang","seat_type":"state","state":"Negeri Sembilan","current_name":"Klawang","current_seat":"N.04 Klawang","all_names":["Klawang"],"n_names":1,"first_year":1986,"last_year":2023,"n_contests":9,"founding":{"year":1986,"party":"UMNO","party_uid":"001-UMNO","coalition":"BN","coalition_uid":"001-BN","name":"Shamsul Bahari (Ramli) bin Mat","candidate_uid":"QAA7H","seat_name":"Klawang"},"current_holder":{"party":"AMANAH","party_uid":"046-AMANAH","coalition":"PH","coalition_uid":"007-PH","name":"Bakri bin Sawir","candidate_uid":"JGZBN","year":2023,"margin_perc":6.42,"win_perc":51.2,"run_party":"BERSATU","run_party_uid":"107-BERSATU","run_perc":44.8,"turnout":68.9,"uncontested":false},"parties_won":[{"party":"UMNO","party_uid":"001-UMNO","coalition":"BN","coalition_uid":"001-BN","wins":7},{"party":"AMANAH","party_uid":"046-AMANAH","coalition":"PH","coalition_uid":"007-PH","wins":2}],"n_distinct_winning_parties":2,"dominant_party":{"party":"UMNO","party_uid":"001-UMNO","coalition":"BN","coalition_uid":"001-BN","wins":7},"closest":{"year":1999,"election":"SE-10","win_party":"UMNO","win_party_uid":"001-UMNO","win_coalition":"BN","run_party":"PKN","run_party_uid":"075-PKN","run_coalition":"BA","win_perc":50.6,"run_perc":49.4,"margin_perc":1.15},"biggest_swing":{"year":1990,"election":"SE-08","swing_pp":-19.9,"from_coalition":"BN","to_coalition":"BN","flipped":false,"win_party":"UMNO","win_party_uid":"001-UMNO","win_coalition":"BN","win_perc":56.8,"run_party":"S46","run_party_uid":"062-S46","run_coalition":"APU","run_perc":43.2,"prev_win_perc":76.7},"marginality_rank":{"rank":93,"total":518,"scope":"state seats, SE-15"},"turnout_ref":{"national_avg":69.1,"latest_year":2023},"timeline":[{"year":1986,"election":"SE-07","date":"1986-08-02","seat_name":"Klawang","win_party":"UMNO","win_party_uid":"001-UMNO","win_coalition":"BN","win_coalition_uid":"001-BN","win_name":"Shamsul Bahari (Ramli) bin Mat","win_perc":76.7,"run_party":"PAS","run_party_uid":"004-PAS","run_coalition":"HAK","run_perc":23.3,"margin_perc":53.48,"turnout":69.5,"n_candidates":2,"uncontested":false,"electorate":6503},{"year":1990,"election":"SE-08","date":"1990-10-20","seat_name":"Klawang","win_party":"UMNO","win_party_uid":"001-UMNO","win_coalition":"BN","win_coalition_uid":"001-BN","win_name":"Shamsul Bahari (Ramli) bin Mat","win_perc":56.8,"run_party":"S46","run_party_uid":"062-S46","run_coalition":"APU","run_perc":43.2,"margin_perc":13.63,"turnout":78.6,"n_candidates":2,"uncontested":false,"electorate":7059},{"year":1995,"election":"SE-09","date":"1995-04-24","seat_name":"Klawang","win_party":"UMNO","win_party_uid":"001-UMNO","win_coalition":"BN","win_coalition_uid":"001-BN","win_name":"Shamsul Bahari (Ramli) bin Mat","win_perc":60.1,"run_party":"S46","run_party_uid":"062-S46","run_coalition":"APU","run_perc":38.8,"margin_perc":21.32,"turnout":74.4,"n_candidates":3,"uncontested":false,"electorate":8700},{"year":1999,"election":"SE-10","date":"1999-11-29","seat_name":"Klawang","win_party":"UMNO","win_party_uid":"001-UMNO","win_coalition":"BN","win_coalition_uid":"001-BN","win_name":"Shamsul Bahari (Ramli) bin Mat","win_perc":50.6,"run_party":"PKN","run_party_uid":"075-PKN","run_coalition":"BA","run_perc":49.4,"margin_perc":1.15,"turnout":72.5,"n_candidates":2,"uncontested":false,"electorate":8542},{"year":2004,"election":"SE-11","date":"2004-03-21","seat_name":"Klawang","win_party":"UMNO","win_party_uid":"001-UMNO","win_coalition":"BN","win_coalition_uid":"001-BN","win_name":"Jalaluddin bin Alias","win_perc":61.3,"run_party":"PAS","run_party_uid":"004-PAS","run_coalition":"BA","run_perc":38.7,"margin_perc":22.54,"turnout":69.8,"n_candidates":2,"uncontested":false,"electorate":8551},{"year":2008,"election":"SE-12","date":"2008-03-08","seat_name":"Klawang","win_party":"UMNO","win_party_uid":"001-UMNO","win_coalition":"BN","win_coalition_uid":"001-BN","win_name":"Yunus bin Rahmat","win_perc":57.1,"run_party":"PAS","run_party_uid":"004-PAS","run_coalition":"PR","run_perc":42.9,"margin_perc":14.21,"turnout":74.3,"n_candidates":2,"uncontested":false,"electorate":8448},{"year":2013,"election":"SE-13","date":"2013-05-05","seat_name":"Klawang","win_party":"UMNO","win_party_uid":"001-UMNO","win_coalition":"BN","win_coalition_uid":"001-BN","win_name":"Yunus bin Rahmat","win_perc":51.8,"run_party":"PAS","run_party_uid":"004-PAS","run_coalition":"PR","run_perc":48.2,"margin_perc":3.56,"turnout":85.1,"n_candidates":2,"uncontested":false,"electorate":9494},{"year":2018,"election":"SE-14","date":"2018-05-09","seat_name":"Klawang","win_party":"AMANAH","win_party_uid":"046-AMANAH","win_coalition":"PH","win_coalition_uid":"007-PH","win_name":"Bakri bin Sawir","win_perc":51.4,"run_party":"UMNO","run_party_uid":"001-UMNO","run_coalition":"BN","run_perc":39.7,"margin_perc":11.67,"turnout":83.1,"n_candidates":3,"uncontested":false,"electorate":10264},{"year":2023,"election":"SE-15","date":"2023-08-12","seat_name":"Klawang","win_party":"AMANAH","win_party_uid":"046-AMANAH","win_coalition":"PH","win_coalition_uid":"007-PH","win_name":"Bakri bin Sawir","win_perc":51.2,"run_party":"BERSATU","run_party_uid":"107-BERSATU","run_coalition":"PN","run_perc":44.8,"margin_perc":6.42,"turnout":68.9,"n_candidates":3,"uncontested":false,"electorate":13163}]}