{"slug":"n-perak-belanja","seat_type":"state","state":"Perak","current_name":"Belanja","current_seat":"N.39 Belanja","all_names":["Belanja"],"n_names":1,"first_year":1974,"last_year":2022,"n_contests":12,"founding":{"year":1974,"party":"UMNO","party_uid":"001-UMNO","coalition":"BN","coalition_uid":"001-BN","name":"Hisan bin Ibrahim","candidate_uid":"GSXVD","seat_name":"Belanja"},"current_holder":{"party":"UMNO","party_uid":"001-UMNO","coalition":"BN","coalition_uid":"001-BN","name":"Khairudin bin Abu Hanipah","candidate_uid":"RDR5W","year":2022,"margin_perc":9.02,"win_perc":47.0,"run_party":"BERSATU","run_party_uid":"107-BERSATU","run_perc":38.0,"turnout":77.8,"uncontested":false},"parties_won":[{"party":"UMNO","party_uid":"001-UMNO","coalition":"BN","coalition_uid":"001-BN","wins":11},{"party":"PAS","party_uid":"004-PAS","coalition":"BA","coalition_uid":"007-BA","wins":1}],"n_distinct_winning_parties":2,"dominant_party":{"party":"UMNO","party_uid":"001-UMNO","coalition":"BN","coalition_uid":"001-BN","wins":11},"closest":{"year":1999,"election":"SE-10","win_party":"PAS","win_party_uid":"004-PAS","win_coalition":"BA","run_party":"UMNO","run_party_uid":"001-UMNO","run_coalition":"BN","win_perc":50.5,"run_perc":49.5,"margin_perc":1.01},"biggest_swing":{"year":1999,"election":"SE-10","swing_pp":-22.0,"from_coalition":"BN","to_coalition":"BA","flipped":true,"win_party":"PAS","win_party_uid":"004-PAS","win_coalition":"BA","win_perc":50.5,"run_party":"UMNO","run_party_uid":"001-UMNO","run_coalition":"BN","run_perc":49.5,"prev_win_perc":72.5},"marginality_rank":{"rank":125,"total":518,"scope":"state seats, SE-15"},"turnout_ref":{"national_avg":69.1,"latest_year":2022},"timeline":[{"year":1974,"election":"SE-04","date":"1974-08-24","seat_name":"Belanja","win_party":"UMNO","win_party_uid":"001-UMNO","win_coalition":"BN","win_coalition_uid":"001-BN","win_name":"Hisan bin Ibrahim","win_perc":59.0,"run_party":"DAP","run_party_uid":"021-DAP","run_coalition":"ALONE","run_perc":32.0,"margin_perc":26.98,"turnout":78.5,"n_candidates":4,"uncontested":false,"electorate":14311},{"year":1978,"election":"SE-05","date":"1978-07-08","seat_name":"Belanja","win_party":"UMNO","win_party_uid":"001-UMNO","win_coalition":"BN","win_coalition_uid":"001-BN","win_name":"Ahmad Azizuddin bin Zainal Abidin","win_perc":50.7,"run_party":"DAP","run_party_uid":"021-DAP","run_coalition":"ALONE","run_perc":30.1,"margin_perc":20.61,"turnout":79.4,"n_candidates":3,"uncontested":false,"electorate":15904},{"year":1982,"election":"SE-06","date":"1982-04-22","seat_name":"Belanja","win_party":"UMNO","win_party_uid":"001-UMNO","win_coalition":"BN","win_coalition_uid":"001-BN","win_name":"Ahmad Azizuddin bin Zainal Abidin","win_perc":null,"run_party":null,"run_party_uid":null,"run_coalition":null,"run_perc":null,"margin_perc":null,"turnout":null,"n_candidates":1,"uncontested":true,"electorate":17864},{"year":1986,"election":"SE-07","date":"1986-08-02","seat_name":"Belanja","win_party":"UMNO","win_party_uid":"001-UMNO","win_coalition":"BN","win_coalition_uid":"001-BN","win_name":"Zainab binti Ibrahim","win_perc":55.0,"run_party":"PAS","run_party_uid":"004-PAS","run_coalition":"HAK","run_perc":45.0,"margin_perc":10.0,"turnout":69.2,"n_candidates":2,"uncontested":false,"electorate":16183},{"year":1990,"election":"SE-08","date":"1990-10-20","seat_name":"Belanja","win_party":"UMNO","win_party_uid":"001-UMNO","win_coalition":"BN","win_coalition_uid":"001-BN","win_name":"Zainab binti Ibrahim","win_perc":61.1,"run_party":"S46","run_party_uid":"062-S46","run_coalition":"APU","run_perc":38.9,"margin_perc":22.29,"turnout":69.1,"n_candidates":2,"uncontested":false,"electorate":17466},{"year":1995,"election":"SE-09","date":"1995-04-24","seat_name":"Belanja","win_party":"UMNO","win_party_uid":"001-UMNO","win_coalition":"BN","win_coalition_uid":"001-BN","win_name":"Mohd Zaim bin Abu Hasan","win_perc":72.5,"run_party":"PAS","run_party_uid":"004-PAS","run_coalition":"APU","run_perc":27.5,"margin_perc":44.92,"turnout":66.3,"n_candidates":2,"uncontested":false,"electorate":16684},{"year":1999,"election":"SE-10","date":"1999-11-29","seat_name":"Belanja","win_party":"PAS","win_party_uid":"004-PAS","win_coalition":"BA","win_coalition_uid":"007-BA","win_name":"Faizol Fadzli bin Mohamed","win_perc":50.5,"run_party":"UMNO","run_party_uid":"001-UMNO","run_coalition":"BN","run_perc":49.5,"margin_perc":1.01,"turnout":66.9,"n_candidates":2,"uncontested":false,"electorate":18066},{"year":2004,"election":"SE-11","date":"2004-03-21","seat_name":"Belanja","win_party":"UMNO","win_party_uid":"001-UMNO","win_coalition":"BN","win_coalition_uid":"001-BN","win_name":"Mohd Zaim bin Abu Hasan","win_perc":64.7,"run_party":"PAS","run_party_uid":"004-PAS","run_coalition":"BA","run_perc":35.3,"margin_perc":29.4,"turnout":73.6,"n_candidates":2,"uncontested":false,"electorate":14824},{"year":2008,"election":"SE-12","date":"2008-03-08","seat_name":"Belanja","win_party":"UMNO","win_party_uid":"001-UMNO","win_coalition":"BN","win_coalition_uid":"001-BN","win_name":"Mohd Zaim bin Abu Hasan","win_perc":60.6,"run_party":"PAS","run_party_uid":"004-PAS","run_coalition":"PR","run_perc":39.4,"margin_perc":21.23,"turnout":77.1,"n_candidates":2,"uncontested":false,"electorate":14470},{"year":2013,"election":"SE-13","date":"2013-05-05","seat_name":"Belanja","win_party":"UMNO","win_party_uid":"001-UMNO","win_coalition":"BN","win_coalition_uid":"001-BN","win_name":"Mohd Nizar bin Zakaria","win_perc":61.9,"run_party":"PAS","run_party_uid":"004-PAS","run_coalition":"PR","run_perc":38.1,"margin_perc":23.86,"turnout":84.4,"n_candidates":2,"uncontested":false,"electorate":15010},{"year":2018,"election":"SE-14","date":"2018-05-09","seat_name":"Belanja","win_party":"UMNO","win_party_uid":"001-UMNO","win_coalition":"BN","win_coalition_uid":"001-BN","win_name":"Khairudin bin Abu Hanipah","win_perc":49.4,"run_party":"PAS","run_party_uid":"004-PAS","run_coalition":"GS","run_perc":26.5,"margin_perc":22.93,"turnout":81.2,"n_candidates":3,"uncontested":false,"electorate":14946},{"year":2022,"election":"SE-15","date":"2022-11-19","seat_name":"Belanja","win_party":"UMNO","win_party_uid":"001-UMNO","win_coalition":"BN","win_coalition_uid":"001-BN","win_name":"Khairudin bin Abu Hanipah","win_perc":47.0,"run_party":"BERSATU","run_party_uid":"107-BERSATU","run_coalition":"PN","run_perc":38.0,"margin_perc":9.02,"turnout":77.8,"n_candidates":4,"uncontested":false,"electorate":17767}]}