{"slug":"n-sarawak-sebuyau","seat_type":"state","state":"Sarawak","current_name":"Sebuyau","current_seat":"N.27 Sebuyau","all_names":["Sebuyau"],"n_names":1,"first_year":1991,"last_year":2021,"n_contests":7,"founding":{"year":1991,"party":"PBB","party_uid":"029-PBB","coalition":"BN","coalition_uid":"001-BN","name":"Julaihi bin Narawi","candidate_uid":"CBXWT","seat_name":"Sebuyau"},"current_holder":{"party":"PBB","party_uid":"029-PBB","coalition":"GPS","coalition_uid":"009-GPS","name":"Julaihi bin Narawi","candidate_uid":"CBXWT","year":2021,"margin_perc":66.4,"win_perc":79.3,"run_party":"AMANAH","run_party_uid":"046-AMANAH","run_perc":12.9,"turnout":68.2,"uncontested":false},"parties_won":[{"party":"PBB","party_uid":"029-PBB","coalition":"BN","coalition_uid":"001-BN","wins":7}],"n_distinct_winning_parties":1,"dominant_party":{"party":"PBB","party_uid":"029-PBB","coalition":"BN","coalition_uid":"001-BN","wins":7},"closest":{"year":2011,"election":"SE-10","win_party":"PBB","win_party_uid":"029-PBB","win_coalition":"BN","run_party":"PAS","run_party_uid":"004-PAS","run_coalition":"PR","win_perc":68.8,"run_perc":30.1,"margin_perc":38.7},"biggest_swing":{"year":2001,"election":"SE-08","swing_pp":16.3,"from_coalition":"BN","to_coalition":"BN","flipped":false,"win_party":"PBB","win_party_uid":"029-PBB","win_coalition":"BN","win_perc":78.6,"run_party":"PKR","run_party_uid":"078-PKR","run_coalition":"ALONE","run_perc":16.2,"prev_win_perc":62.3},"marginality_rank":{"rank":571,"total":585,"scope":"state seats, SE-12"},"turnout_ref":{"national_avg":76.4,"latest_year":2021},"timeline":[{"year":1991,"election":"SE-06","date":"1991-09-27","seat_name":"Sebuyau","win_party":"PBB","win_party_uid":"029-PBB","win_coalition":"BN","win_coalition_uid":"001-BN","win_name":"Julaihi bin Narawi","win_perc":62.3,"run_party":"PBDS","run_party_uid":"049-PBDS","run_coalition":"ALONE","run_perc":23.2,"margin_perc":39.06,"turnout":73.2,"n_candidates":5,"uncontested":false,"electorate":8009},{"year":1996,"election":"SE-07","date":"1996-09-07","seat_name":"Sebuyau","win_party":"PBB","win_party_uid":"029-PBB","win_coalition":"BN","win_coalition_uid":"001-BN","win_name":"Julaihi bin Narawi","win_perc":null,"run_party":null,"run_party_uid":null,"run_coalition":null,"run_perc":null,"margin_perc":null,"turnout":null,"n_candidates":1,"uncontested":true,"electorate":10335},{"year":2001,"election":"SE-08","date":"2001-09-27","seat_name":"Sebuyau","win_party":"PBB","win_party_uid":"029-PBB","win_coalition":"BN","win_coalition_uid":"001-BN","win_name":"Julaihi bin Narawi","win_perc":78.6,"run_party":"PKR","run_party_uid":"078-PKR","run_coalition":"ALONE","run_perc":16.2,"margin_perc":62.37,"turnout":67.3,"n_candidates":3,"uncontested":false,"electorate":9972},{"year":2006,"election":"SE-09","date":"2006-05-20","seat_name":"Sebuyau","win_party":"PBB","win_party_uid":"029-PBB","win_coalition":"BN","win_coalition_uid":"001-BN","win_name":"Julaihi bin Narawi","win_perc":74.2,"run_party":"PKR","run_party_uid":"078-PKR","run_coalition":"ALONE","run_perc":25.8,"margin_perc":48.49,"turnout":68.1,"n_candidates":2,"uncontested":false,"electorate":7549},{"year":2011,"election":"SE-10","date":"2011-04-16","seat_name":"Sebuyau","win_party":"PBB","win_party_uid":"029-PBB","win_coalition":"BN","win_coalition_uid":"001-BN","win_name":"Julaihi bin Narawi","win_perc":68.8,"run_party":"PAS","run_party_uid":"004-PAS","run_coalition":"PR","run_perc":30.1,"margin_perc":38.7,"turnout":74.3,"n_candidates":3,"uncontested":false,"electorate":8042},{"year":2016,"election":"SE-11","date":"2016-05-07","seat_name":"Sebuyau","win_party":"PBB","win_party_uid":"029-PBB","win_coalition":"BN","win_coalition_uid":"001-BN","win_name":"Julaihi bin Narawi","win_perc":69.9,"run_party":"PAS","run_party_uid":"004-PAS","run_coalition":"ALONE","run_perc":27.6,"margin_perc":42.29,"turnout":73.2,"n_candidates":3,"uncontested":false,"electorate":9041},{"year":2021,"election":"SE-12","date":"2021-12-18","seat_name":"Sebuyau","win_party":"PBB","win_party_uid":"029-PBB","win_coalition":"GPS","win_coalition_uid":"009-GPS","win_name":"Julaihi bin Narawi","win_perc":79.3,"run_party":"AMANAH","run_party_uid":"046-AMANAH","run_coalition":"PH","run_perc":12.9,"margin_perc":66.4,"turnout":68.2,"n_candidates":3,"uncontested":false,"electorate":9367}]}