{"slug":"p-johor-labis","seat_type":"federal","state":"Johor","current_name":"Labis","current_seat":"P.142 Labis","all_names":["Labis"],"n_names":1,"first_year":1974,"last_year":2022,"n_contests":12,"founding":{"year":1974,"party":"UMNO","party_uid":"001-UMNO","coalition":"BN","coalition_uid":"001-BN","name":"Musa bin Hitam","candidate_uid":"S09CJ","seat_name":"Labis"},"current_holder":{"party":"DAP","party_uid":"021-DAP","coalition":"PH","coalition_uid":"007-PH","name":"Pang Hok Liong","candidate_uid":"GZSAT","year":2022,"margin_perc":8.15,"win_perc":46.4,"run_party":"MCA","run_party_uid":"003-MCA","run_perc":38.3,"turnout":70.8,"uncontested":false},"parties_won":[{"party":"MCA","party_uid":"003-MCA","coalition":"BN","coalition_uid":"001-BN","wins":7},{"party":"UMNO","party_uid":"001-UMNO","coalition":"BN","coalition_uid":"001-BN","wins":3},{"party":"DAP","party_uid":"021-DAP","coalition":"PH","coalition_uid":"007-PH","wins":2}],"n_distinct_winning_parties":3,"dominant_party":{"party":"MCA","party_uid":"003-MCA","coalition":"BN","coalition_uid":"001-BN","wins":7},"closest":{"year":2013,"election":"GE-13","win_party":"MCA","win_party_uid":"003-MCA","win_coalition":"BN","run_party":"DAP","run_party_uid":"021-DAP","run_coalition":"PR","win_perc":50.6,"run_perc":49.4,"margin_perc":1.13},"biggest_swing":{"year":1986,"election":"GE-07","swing_pp":-20.1,"from_coalition":"BN","to_coalition":"BN","flipped":false,"win_party":"MCA","win_party_uid":"003-MCA","win_coalition":"BN","win_perc":68.0,"run_party":"DAP","run_party_uid":"021-DAP","run_coalition":"ALONE","run_perc":32.0,"prev_year":1978,"prev_win_party":"UMNO","prev_win_party_uid":"001-UMNO","prev_win_perc":88.0,"prev_run_party":"PAS","prev_run_party_uid":"004-PAS","prev_run_perc":12.0},"marginality_rank":{"rank":57,"total":222,"scope":"federal seats, GE-15 (2022)"},"turnout_ref":{"national_avg":73.4,"latest_year":2022},"timeline":[{"year":1974,"election":"GE-04","date":"1974-08-24","seat_name":"Labis","win_party":"UMNO","win_party_uid":"001-UMNO","win_coalition":"BN","win_coalition_uid":"001-BN","win_name":"Musa bin Hitam","win_perc":null,"run_party":null,"run_party_uid":null,"run_coalition":null,"run_perc":null,"margin_perc":null,"turnout":null,"n_candidates":1,"uncontested":true,"electorate":25469},{"year":1978,"election":"GE-05","date":"1978-07-08","seat_name":"Labis","win_party":"UMNO","win_party_uid":"001-UMNO","win_coalition":"BN","win_coalition_uid":"001-BN","win_name":"Musa bin Hitam","win_perc":88.0,"run_party":"PAS","run_party_uid":"004-PAS","run_coalition":"ALONE","run_perc":12.0,"margin_perc":76.08,"turnout":78.4,"n_candidates":2,"uncontested":false,"electorate":30305},{"year":1982,"election":"GE-06","date":"1982-04-22","seat_name":"Labis","win_party":"UMNO","win_party_uid":"001-UMNO","win_coalition":"BN","win_coalition_uid":"001-BN","win_name":"Bahari bin Haron","win_perc":null,"run_party":null,"run_party_uid":null,"run_coalition":null,"run_perc":null,"margin_perc":null,"turnout":null,"n_candidates":1,"uncontested":true,"electorate":36950},{"year":1986,"election":"GE-07","date":"1986-08-02","seat_name":"Labis","win_party":"MCA","win_party_uid":"003-MCA","win_coalition":"BN","win_coalition_uid":"001-BN","win_name":"Ling Liong Sik","win_perc":68.0,"run_party":"DAP","run_party_uid":"021-DAP","run_coalition":"ALONE","run_perc":32.0,"margin_perc":35.92,"turnout":72.3,"n_candidates":2,"uncontested":false,"electorate":38264},{"year":1990,"election":"GE-08","date":"1990-10-20","seat_name":"Labis","win_party":"MCA","win_party_uid":"003-MCA","win_coalition":"BN","win_coalition_uid":"001-BN","win_name":"Ling Liong Sik","win_perc":58.7,"run_party":"DAP","run_party_uid":"021-DAP","run_coalition":"GR","run_perc":41.3,"margin_perc":17.3,"turnout":74.1,"n_candidates":2,"uncontested":false,"electorate":42252},{"year":1995,"election":"GE-09","date":"1995-04-24","seat_name":"Labis","win_party":"MCA","win_party_uid":"003-MCA","win_coalition":"BN","win_coalition_uid":"001-BN","win_name":"Ling Liong Sik","win_perc":72.6,"run_party":"DAP","run_party_uid":"021-DAP","run_coalition":"GR","run_perc":27.4,"margin_perc":45.15,"turnout":73.2,"n_candidates":2,"uncontested":false,"electorate":47413},{"year":1999,"election":"GE-10","date":"1999-11-29","seat_name":"Labis","win_party":"MCA","win_party_uid":"003-MCA","win_coalition":"BN","win_coalition_uid":"001-BN","win_name":"Ling Liong Sik","win_perc":70.5,"run_party":"DAP","run_party_uid":"021-DAP","run_coalition":"BA","run_perc":29.5,"margin_perc":41.05,"turnout":71.4,"n_candidates":2,"uncontested":false,"electorate":48674},{"year":2004,"election":"GE-11","date":"2004-03-21","seat_name":"Labis","win_party":"MCA","win_party_uid":"003-MCA","win_coalition":"BN","win_coalition_uid":"001-BN","win_name":"Chua Soi Lek","win_perc":74.2,"run_party":"DAP","run_party_uid":"021-DAP","run_coalition":"ALONE","run_perc":25.8,"margin_perc":48.31,"turnout":71.0,"n_candidates":2,"uncontested":false,"electorate":32518},{"year":2008,"election":"GE-12","date":"2008-03-08","seat_name":"Labis","win_party":"MCA","win_party_uid":"003-MCA","win_coalition":"BN","win_coalition_uid":"001-BN","win_name":"Chua Tee Yong","win_perc":58.8,"run_party":"DAP","run_party_uid":"021-DAP","run_coalition":"PR","run_perc":41.2,"margin_perc":17.63,"turnout":71.9,"n_candidates":2,"uncontested":false,"electorate":33468},{"year":2013,"election":"GE-13","date":"2013-05-05","seat_name":"Labis","win_party":"MCA","win_party_uid":"003-MCA","win_coalition":"BN","win_coalition_uid":"001-BN","win_name":"Chua Tee Yong","win_perc":50.6,"run_party":"DAP","run_party_uid":"021-DAP","run_coalition":"PR","run_perc":49.4,"margin_perc":1.13,"turnout":84.9,"n_candidates":2,"uncontested":false,"electorate":37714},{"year":2018,"election":"GE-14","date":"2018-05-09","seat_name":"Labis","win_party":"DAP","win_party_uid":"021-DAP","win_coalition":"PH","win_coalition_uid":"007-PH","win_name":"Pang Hok Liong","win_perc":52.1,"run_party":"MCA","run_party_uid":"003-MCA","run_coalition":"BN","run_perc":41.6,"margin_perc":10.47,"turnout":82.1,"n_candidates":3,"uncontested":false,"electorate":40356},{"year":2022,"election":"GE-15","date":"2022-11-19","seat_name":"Labis","win_party":"DAP","win_party_uid":"021-DAP","win_coalition":"PH","win_coalition_uid":"007-PH","win_name":"Pang Hok Liong","win_perc":46.4,"run_party":"MCA","run_party_uid":"003-MCA","run_coalition":"BN","run_perc":38.3,"margin_perc":8.15,"turnout":70.8,"n_candidates":3,"uncontested":false,"electorate":49846}]}