{"slug":"p-perak-ipoh-barat","seat_type":"federal","state":"Perak","current_name":"Ipoh Barat","current_seat":"P.065 Ipoh Barat","all_names":["Ipoh Barat"],"n_names":1,"first_year":1995,"last_year":2022,"n_contests":7,"founding":{"year":1995,"party":"MCA","party_uid":"003-MCA","coalition":"BN","coalition_uid":"001-BN","name":"Ho Cheong Sing","candidate_uid":"NC2QE","seat_name":"Ipoh Barat"},"current_holder":{"party":"DAP","party_uid":"021-DAP","coalition":"PH","coalition_uid":"007-PH","name":"M. Kulasegaran a/l V. Murugeson ","candidate_uid":"8H5R5","year":2022,"margin_perc":72.32,"win_perc":81.6,"run_party":"MCA","run_party_uid":"003-MCA","run_perc":9.3,"turnout":69.2,"uncontested":false},"parties_won":[{"party":"DAP","party_uid":"021-DAP","coalition":"ALONE","coalition_uid":"000-ALONE","wins":5},{"party":"MCA","party_uid":"003-MCA","coalition":"BN","coalition_uid":"001-BN","wins":2}],"n_distinct_winning_parties":2,"dominant_party":{"party":"DAP","party_uid":"021-DAP","coalition":"ALONE","coalition_uid":"000-ALONE","wins":5},"closest":{"year":2004,"election":"GE-11","win_party":"DAP","win_party_uid":"021-DAP","win_coalition":"ALONE","run_party":"MCA","run_party_uid":"003-MCA","run_coalition":"BN","win_perc":50.7,"run_perc":49.3,"margin_perc":1.32},"biggest_swing":{"year":2008,"election":"GE-12","swing_pp":15.0,"from_coalition":"ALONE","to_coalition":"PR","flipped":true,"win_party":"DAP","win_party_uid":"021-DAP","win_coalition":"PR","win_perc":65.7,"run_party":"MCA","run_party_uid":"003-MCA","run_coalition":"BN","run_perc":34.3,"prev_year":2004,"prev_win_party":"DAP","prev_win_party_uid":"021-DAP","prev_win_perc":50.7,"prev_run_party":"MCA","prev_run_party_uid":"003-MCA","prev_run_perc":49.3},"marginality_rank":{"rank":213,"total":222,"scope":"federal seats, GE-15 (2022)"},"turnout_ref":{"national_avg":73.4,"latest_year":2022},"timeline":[{"year":1995,"election":"GE-09","date":"1995-04-24","seat_name":"Ipoh Barat","win_party":"MCA","win_party_uid":"003-MCA","win_coalition":"BN","win_coalition_uid":"001-BN","win_name":"Ho Cheong Sing","win_perc":55.5,"run_party":"DAP","run_party_uid":"021-DAP","run_coalition":"GR","run_perc":44.5,"margin_perc":10.98,"turnout":68.7,"n_candidates":2,"uncontested":false,"electorate":66502},{"year":1999,"election":"GE-10","date":"1999-11-29","seat_name":"Ipoh Barat","win_party":"MCA","win_party_uid":"003-MCA","win_coalition":"BN","win_coalition_uid":"001-BN","win_name":"Ho Cheong Sing","win_perc":53.7,"run_party":"DAP","run_party_uid":"021-DAP","run_coalition":"BA","run_perc":45.8,"margin_perc":7.85,"turnout":68.2,"n_candidates":3,"uncontested":false,"electorate":71355},{"year":2004,"election":"GE-11","date":"2004-03-21","seat_name":"Ipoh Barat","win_party":"DAP","win_party_uid":"021-DAP","win_coalition":"ALONE","win_coalition_uid":"000-ALONE","win_name":"M. Kulasegaran a/l V. Murugeson ","win_perc":50.7,"run_party":"MCA","run_party_uid":"003-MCA","run_coalition":"BN","run_perc":49.3,"margin_perc":1.32,"turnout":68.4,"n_candidates":2,"uncontested":false,"electorate":68394},{"year":2008,"election":"GE-12","date":"2008-03-08","seat_name":"Ipoh Barat","win_party":"DAP","win_party_uid":"021-DAP","win_coalition":"PR","win_coalition_uid":"007-PR","win_name":"M. Kulasegaran a/l V. Murugeson ","win_perc":65.7,"run_party":"MCA","run_party_uid":"003-MCA","run_coalition":"BN","run_perc":34.3,"margin_perc":31.31,"turnout":72.6,"n_candidates":2,"uncontested":false,"electorate":69773},{"year":2013,"election":"GE-13","date":"2013-05-05","seat_name":"Ipoh Barat","win_party":"DAP","win_party_uid":"021-DAP","win_coalition":"PR","win_coalition_uid":"007-PR","win_name":"M. Kulasegaran a/l V. Murugeson ","win_perc":73.2,"run_party":"MCA","run_party_uid":"003-MCA","run_coalition":"BN","run_perc":26.4,"margin_perc":46.81,"turnout":81.1,"n_candidates":3,"uncontested":false,"electorate":77761},{"year":2018,"election":"GE-14","date":"2018-05-09","seat_name":"Ipoh Barat","win_party":"DAP","win_party_uid":"021-DAP","win_coalition":"PH","win_coalition_uid":"007-PH","win_name":"M. Kulasegaran a/l V. Murugeson ","win_perc":84.9,"run_party":"MCA","run_party_uid":"003-MCA","run_coalition":"BN","run_perc":15.1,"margin_perc":69.81,"turnout":78.8,"n_candidates":2,"uncontested":false,"electorate":84874},{"year":2022,"election":"GE-15","date":"2022-11-19","seat_name":"Ipoh Barat","win_party":"DAP","win_party_uid":"021-DAP","win_coalition":"PH","win_coalition_uid":"007-PH","win_name":"M. Kulasegaran a/l V. Murugeson ","win_perc":81.6,"run_party":"MCA","run_party_uid":"003-MCA","run_coalition":"BN","run_perc":9.3,"margin_perc":72.32,"turnout":69.2,"n_candidates":4,"uncontested":false,"electorate":114654}]}